logforge/__init__.py
logforge/audit/__init__.py
logforge/audit/apps.py
logforge/audit/soft_delete.py
logforge/audit/tasks.py
logforge/audit/urls.py
logforge/audit/views.py
logforge/audit/config/__init__.py
logforge/audit/config/settings.py
logforge/audit/contracts/__init__.py
logforge/audit/contracts/log_writer.py
logforge/audit/management/__init__.py
logforge/audit/middleware/__init__.py
logforge/audit/middleware/request_context.py
logforge/audit/migrations/0001_initial.py
logforge/audit/migrations/__init__.py
logforge/audit/mixins/__init__.py
logforge/audit/mixins/logs_activity.py
logforge/audit/models/__init__.py
logforge/audit/models/activity_log.py
logforge/audit/static/logforge/app.css
logforge/audit/static/logforge/app.js
logforge/audit/support/__init__.py
logforge/audit/support/audit_batch.py
logforge/audit/templates/logforge/dashboard/log-view.html
logforge/audit/templates/logforge/dashboard/logs.html
logforge/audit/writers/__init__.py
logforge/audit/writers/database_writer.py
logforge/audit/writers/queue_writer.py
logforge_django-0.1.3.dist-info/licenses/LICENSE
logforge_django-0.1.3.dist-info/METADATA
logforge_django-0.1.3.dist-info/WHEEL
logforge_django-0.1.3.dist-info/top_level.txt
logforge_django-0.1.3.dist-info/RECORD
